[{"appcode":"function OnUpdate(doc, meta) {\n    var repitition = 100\n\n\tfor (let i = 0; i < repitition; i++) {\t  \n        meta.id = generateUUID();\n        tgt[meta.id]=doc;\n    }\n}\n\nfunction generateUUID() {\n  // Generate a random number\n  var d = new Date().getTime();\n  if (typeof performance !== 'undefined' && typeof performance.now === 'function'){\n      d += performance.now(); // use high-precision timer if available\n  }\n  \n  // Format the UUID\n  var uuid = 'xxxxxxxx-xxxx-4xxx-yxxx-xxxxxxxxxxxx'.replace(/[xy]/g, function(c) {\n    var r = (d + Math.random() * 16) % 16 | 0;\n    d = Math.floor(d / 16);\n    return (c === 'x' ? r : (r & 0x3 | 0x8)).toString(16);\n  });\n\n  return uuid;\n}","depcfg":{"buckets":[{"alias":"tgt","bucket_name":"vector-sample","scope_name":"color","collection_name":"transitory","access":"rw"}],"source_bucket":"eventing","source_scope":"_default","source_collection":"raw","metadata_bucket":"eventing","metadata_scope":"_default","metadata_collection":"_default"},"version":"","enforce_schema":false,"handleruuid":3936096875,"function_instance_id":"HE9vz3","appname":"generate_transitory_data","settings":{"cursor_aware":false,"dcp_stream_boundary":"everything","deadline_timeout":62,"deployment_status":false,"description":"","execution_timeout":60,"language_compatibility":"6.6.2","log_level":"INFO","n1ql_consistency":"none","num_timer_partitions":160,"processing_status":false,"timer_context_size":1024,"user_prefix":"eventing","worker_count":10},"function_scope":{"bucket":"*","scope":"*"}}]